[{"name":"Gytis","surname":"Leonavi\u010dius","account_nr":"LT571010047145464656","social_id":"38503150022","password":"202cb962ac59075b964b07152d234b70","funds":"0","id":1},{"name":"Petras","surname":"Petraitis","account_nr":"LT461010074451413353","social_id":"38612318822","password":"202cb962ac59075b964b07152d234b70","funds":"0","id":2},{"name":"Jonas","surname":"Jonaitis","account_nr":"LT441010090913965314","social_id":"38503150088","password":"202cb962ac59075b964b07152d234b70","funds":"0","id":3},{"name":"Tomas","surname":"Tomaitis","account_nr":"LT511010046781090360","social_id":"38503150000","password":"202cb962ac59075b964b07152d234b70","funds":"0","id":4}]